{
    "best_exp_npcs": [
        {
            "code": "NPC590",
            "name": "Rey Drag\u00f3n",
            "exp": 432694,
            "gold": 360000,
            "min_hp": 800000,
            "max_hp": 800000,
            "damage": 415.0,
            "min_hit": 400,
            "max_hit": 430,
            "def_": 650,
            "attack_power": 415.0,
            "evasion_power": 0,
            "level": 100
        },
        {
            "code": "NPC520",
            "name": "Arnarak",
            "exp": 274099,
            "gold": 500000,
            "min_hp": 600000,
            "max_hp": 600000,
            "damage": 275.0,
            "min_hit": 150,
            "max_hit": 400,
            "def_": 40,
            "attack_power": 275.0,
            "evasion_power": 0,
            "level": 100
        },
        {
            "code": "NPC645",
            "name": "Jefe Heraldo del Mal",
            "exp": 392959,
            "gold": 600000,
            "min_hp": 1000000,
            "max_hp": 1000000,
            "damage": 485.0,
            "min_hit": 440,
            "max_hit": 530,
            "def_": 45,
            "attack_power": 485.0,
            "evasion_power": 0,
            "level": 100
        },
        {
            "code": "NPC668",
            "name": "Dragon Pragon",
            "exp": 329932,
            "gold": 360000,
            "min_hp": 800000,
            "max_hp": 800000,
            "damage": 415.0,
            "min_hit": 400,
            "max_hit": 430,
            "def_": 650,
            "attack_power": 415.0,
            "evasion_power": 0,
            "level": 100
        },
        {
            "code": "NPC639",
            "name": "Jefe Oct\u00e1pudus",
            "exp": 120103,
            "gold": 1000000,
            "min_hp": 250000,
            "max_hp": 250000,
            "damage": 187.5,
            "min_hit": 175,
            "max_hit": 200,
            "def_": 60,
            "attack_power": 187.5,
            "evasion_power": 0,
            "level": 100
        },
        {
            "code": "NPC634",
            "name": "Jefe de las Profundidades",
            "exp": 305924,
            "gold": 2000000,
            "min_hp": 700000,
            "max_hp": 700000,
            "damage": 495.0,
            "min_hit": 480,
            "max_hit": 510,
            "def_": 25,
            "attack_power": 495.0,
            "evasion_power": 0,
            "level": 100
        },
        {
            "code": "NPC511",
            "name": "Drag\u00f3n Legendario",
            "exp": 243162,
            "gold": 250000,
            "min_hp": 650000,
            "max_hp": 650000,
            "damage": 410.0,
            "min_hit": 400,
            "max_hit": 420,
            "def_": 400,
            "attack_power": 410.0,
            "evasion_power": 0,
            "level": 100
        },
        {
            "code": "NPC607",
            "name": "El Abominable Grinch",
            "exp": 315397,
            "gold": 500000,
            "min_hp": 750000,
            "max_hp": 750000,
            "damage": 585.0,
            "min_hit": 500,
            "max_hit": 670,
            "def_": 500,
            "attack_power": 585.0,
            "evasion_power": 0,
            "level": 100
        },
        {
            "code": "NPC542",
            "name": "Gran Drag\u00f3n Negro",
            "exp": 145447,
            "gold": 85000,
            "min_hp": 380000,
            "max_hp": 380000,
            "damage": 390.0,
            "min_hit": 380,
            "max_hit": 400,
            "def_": 300,
            "attack_power": 390.0,
            "evasion_power": 0,
            "level": 100
        },
        {
            "code": "NPC633",
            "name": "Jefe Oyaral",
            "exp": 172387,
            "gold": 1250000,
            "min_hp": 400000,
            "max_hp": 400000,
            "damage": 495.0,
            "min_hit": 480,
            "max_hit": 510,
            "def_": 45,
            "attack_power": 495.0,
            "evasion_power": 0,
            "level": 100
        },
        {
            "code": "NPC560",
            "name": "Gran Hechicero Garveloth",
            "exp": 83893,
            "gold": 80000,
            "min_hp": 75000,
            "max_hp": 75000,
            "damage": 275.0,
            "min_hit": 260,
            "max_hit": 290,
            "def_": 20,
            "attack_power": 275.0,
            "evasion_power": 0,
            "level": 100
        },
        {
            "code": "NPC649",
            "name": "Murci\u00e9lago Superior",
            "exp": 535,
            "gold": 1500,
            "min_hp": 1100,
            "max_hp": 1100,
            "damage": 2.0,
            "min_hit": 1,
            "max_hit": 3,
            "def_": 50,
            "attack_power": 2.0,
            "evasion_power": 0,
            "level": 100
        },
        {
            "code": "NPC614",
            "name": "Guardi\u00e1n",
            "exp": 42968,
            "gold": 45000,
            "min_hp": 36250,
            "max_hp": 36250,
            "damage": 260.0,
            "min_hit": 200,
            "max_hit": 320,
            "def_": 25,
            "attack_power": 260.0,
            "evasion_power": 0,
            "level": 100
        },
        {
            "code": "NPC621",
            "name": "Gran Drag\u00f3n Rojo",
            "exp": 56642,
            "gold": 9500,
            "min_hp": 115000,
            "max_hp": 115000,
            "damage": 345.0,
            "min_hit": 320,
            "max_hit": 370,
            "def_": 50,
            "attack_power": 345.0,
            "evasion_power": 0,
            "level": 100
        },
        {
            "code": "NPC581",
            "name": "Golem Infernal",
            "exp": 68555,
            "gold": 60000,
            "min_hp": 150000,
            "max_hp": 150000,
            "damage": 485.0,
            "min_hit": 440,
            "max_hit": 530,
            "def_": 45,
            "attack_power": 485.0,
            "evasion_power": 0,
            "level": 60
        },
        {
            "code": "NPC608",
            "name": "Vampiro Transformado",
            "exp": 37483,
            "gold": 50000,
            "min_hp": 70000,
            "max_hp": 70000,
            "damage": 270.0,
            "min_hit": 260,
            "max_hit": 280,
            "def_": 30,
            "attack_power": 270.0,
            "evasion_power": 0,
            "level": 100
        },
        {
            "code": "NPC587",
            "name": "Golem de hielo",
            "exp": 64374,
            "gold": 80000,
            "min_hp": 175000,
            "max_hp": 175000,
            "damage": 495.0,
            "min_hit": 450,
            "max_hit": 540,
            "def_": 40,
            "attack_power": 495.0,
            "evasion_power": 0,
            "level": 60
        },
        {
            "code": "NPC665",
            "name": "Hechicero Guardian",
            "exp": 13201,
            "gold": 15000,
            "min_hp": 22950,
            "max_hp": 22950,
            "damage": 127.5,
            "min_hit": 120,
            "max_hit": 135,
            "def_": 10,
            "attack_power": 127.5,
            "evasion_power": 0,
            "level": 51
        },
        {
            "code": "NPC664",
            "name": "Hechicero Infernal Corrupto",
            "exp": 12687,
            "gold": 15000,
            "min_hp": 22950,
            "max_hp": 22950,
            "damage": 127.5,
            "min_hit": 120,
            "max_hit": 135,
            "def_": 10,
            "attack_power": 127.5,
            "evasion_power": 0,
            "level": 51
        },
        {
            "code": "NPC512",
            "name": "Hechicero de Fuego",
            "exp": 14312,
            "gold": 15000,
            "min_hp": 24450,
            "max_hp": 24450,
            "damage": 152.5,
            "min_hit": 140,
            "max_hit": 165,
            "def_": 10,
            "attack_power": 152.5,
            "evasion_power": 0,
            "level": 51
        }
    ],
    "best_gold_npcs": [
        {
            "code": "NPC639",
            "name": "Jefe Oct\u00e1pudus",
            "exp": 120103,
            "gold": 1000000,
            "min_hp": 250000,
            "max_hp": 250000,
            "damage": 187.5,
            "min_hit": 175,
            "max_hit": 200,
            "def_": 60,
            "attack_power": 187.5,
            "evasion_power": 0,
            "level": 100
        },
        {
            "code": "NPC634",
            "name": "Jefe de las Profundidades",
            "exp": 305924,
            "gold": 2000000,
            "min_hp": 700000,
            "max_hp": 700000,
            "damage": 495.0,
            "min_hit": 480,
            "max_hit": 510,
            "def_": 25,
            "attack_power": 495.0,
            "evasion_power": 0,
            "level": 100
        },
        {
            "code": "NPC633",
            "name": "Jefe Oyaral",
            "exp": 172387,
            "gold": 1250000,
            "min_hp": 400000,
            "max_hp": 400000,
            "damage": 495.0,
            "min_hit": 480,
            "max_hit": 510,
            "def_": 45,
            "attack_power": 495.0,
            "evasion_power": 0,
            "level": 100
        }
    ],
    "best_total_npc": {
        "code": "NPC639",
        "name": "Jefe Oct\u00e1pudus",
        "exp": 120103,
        "gold": 1000000,
        "min_hp": 250000,
        "max_hp": 250000,
        "damage": 187.5,
        "min_hit": 175,
        "max_hit": 200,
        "def_": 60,
        "attack_power": 187.5,
        "evasion_power": 0,
        "level": 100
    },
    "best_damage_npcs": [
        {
            "code": "NPC500",
            "name": "Murci\u00e9lago",
            "exp": 6,
            "gold": 5,
            "min_hp": 15,
            "max_hp": 15,
            "damage": 1.0,
            "min_hit": 1,
            "max_hit": 1,
            "def_": 0,
            "attack_power": 1.0,
            "evasion_power": 0,
            "level": 5
        },
        {
            "code": "NPC545",
            "name": "Lobo",
            "exp": 150,
            "gold": 0,
            "min_hp": 300,
            "max_hp": 300,
            "damage": 16.0,
            "min_hit": 12,
            "max_hit": 20,
            "def_": 30,
            "attack_power": 16.0,
            "evasion_power": 0,
            "level": 16
        },
        {
            "code": "NPC502",
            "name": "Zombie",
            "exp": 143,
            "gold": 35,
            "min_hp": 280,
            "max_hp": 280,
            "damage": 27.5,
            "min_hit": 25,
            "max_hit": 30,
            "def_": 12,
            "attack_power": 27.5,
            "evasion_power": 0,
            "level": 17
        },
        {
            "code": "NPC501",
            "name": "Lobo",
            "exp": 34,
            "gold": 50,
            "min_hp": 70,
            "max_hp": 70,
            "damage": 15.0,
            "min_hit": 12,
            "max_hit": 18,
            "def_": 8,
            "attack_power": 15.0,
            "evasion_power": 0,
            "level": 10
        },
        {
            "code": "NPC504",
            "name": "Serpiente",
            "exp": 9,
            "gold": 5,
            "min_hp": 18,
            "max_hp": 18,
            "damage": 2.5,
            "min_hit": 2,
            "max_hit": 3,
            "def_": 0,
            "attack_power": 2.5,
            "evasion_power": 0,
            "level": 6
        }
    ]
}